{
  "kind": "singleType",
  "collectionName": "schools",
  "info": {
    "singularName": "school",
    "pluralName": "schools",
    "displayName": "School",
    "description": ""
  },
  "options": {
    "draftAndPublish": true
  },
  "pluginOptions": {
    "i18n": {
      "localized": true
    }
  },
  "attributes": {
    "schools": {
      "type": "component",
      "repeatable": true,
      "component": "timeline-content.school",
      "pluginOptions": {
        "i18n": {
          "localized": true
        }
      }
    }
  }
}
